yt_viewfinder_TheManWhoLikesToCode/__init__.py
yt_viewfinder_TheManWhoLikesToCode/core.py
yt_viewfinder_TheManWhoLikesToCode-2024.1.0.dist-info/LICENSE
yt_viewfinder_TheManWhoLikesToCode-2024.1.0.dist-info/METADATA
yt_viewfinder_TheManWhoLikesToCode-2024.1.0.dist-info/WHEEL
yt_viewfinder_TheManWhoLikesToCode-2024.1.0.dist-info/top_level.txt
yt_viewfinder_TheManWhoLikesToCode-2024.1.0.dist-info/RECORD
